mcpie_cli/__init__.py
mcpie_cli/mcpie.py
mcpie_cli-0.2.0.dist-info/WHEEL
mcpie_cli-0.2.0.dist-info/entry_points.txt
mcpie_cli-0.2.0.dist-info/METADATA
mcpie_cli-0.2.0.dist-info/RECORD
