Metadata-Version: 2.3
Name: mcpie-cli
Version: 0.2.0
Summary: MCP Client for Humans
Keywords: mcp,model-context-protocol,cli,repl,interactive
License: MIT
Requires-Dist: mcp>=1.8.0
Requires-Dist: pygments>=2.19.1
Requires-Dist: prompt-toolkit>=3.0.0
Requires-Dist: rich>=13.0.0
Requires-Dist: click>=8.0.0
Requires-Dist: pyyaml>=6.0.0
Requires-Python: >=3.10
